joshbasiccalculator/__init__.py
datetimetimedate-0.0.1.dist-info/LICENCE.txt
datetimetimedate-0.0.1.dist-info/METADATA
datetimetimedate-0.0.1.dist-info/WHEEL
datetimetimedate-0.0.1.dist-info/top_level.txt
datetimetimedate-0.0.1.dist-info/RECORD
